.gitignore
dist.sh
pyproject.toml
src/eyck/__init__.py
src/eyck/encoder.py
src/eyck/targets.py
src/eyck.egg-info/PKG-INFO
src/eyck.egg-info/SOURCES.txt
src/eyck.egg-info/dependency_links.txt
src/eyck.egg-info/requires.txt
src/eyck.egg-info/top_level.txt
src/eyck/flow/__init__.py
src/eyck/flow/flow.py
src/eyck/flow/flow_template.jinja2
src/eyck/flow/linked.py
src/eyck/flow/memorymap.py
src/eyck/flow/objects.py
src/eyck/flow/tipyte.py
src/eyck/modalities/__init__.py
src/eyck/modalities/clustering/__init__.py
src/eyck/modalities/clustering/clustering.py
src/eyck/modalities/folds/__init__.py
src/eyck/modalities/folds/folds.py
src/eyck/modalities/fragments/__init__.py
src/eyck/modalities/fragments/fragments.py
src/eyck/modalities/fragments/view.py
src/eyck/modalities/fragments/loaders/__init__.py
src/eyck/modalities/fragments/loaders/helpers.c
src/eyck/modalities/fragments/loaders/helpers.pyx
src/eyck/modalities/fragments/loaders/loaders.py
src/eyck/modalities/gradient/__init__.py
src/eyck/modalities/gradient/gradient.py
src/eyck/modalities/regions/__init__.py
src/eyck/modalities/transcriptome/__init__.py
src/eyck/modalities/transcriptome/data.py
src/eyck/modalities/transcriptome/diffexp.py
src/eyck/modalities/transcriptome/plot.py
src/eyck/modalities/transcriptome/timetranscriptome.py
src/eyck/modalities/transcriptome/tools.py
src/eyck/processes/__init__.py
src/eyck/processes/cellcycle/__init__.py
src/eyck/utils/__init__.py
src/eyck/utils/files.py