Metadata-Version: 2.4
Name: eyck
Version: 0.0.15
Summary: Multi-omics data integration
Author-email: Wouter Saelens <wouter.saelens@gmail.com>
License: MIT
Project-URL: Homepage, https://github.com/DeplanckeLab/ChromatinHD
Project-URL: Bug Tracker, https://github.com/DeplanckeLab/ChromatinHD/issues
Keywords: bioinformatics,chromatin accessibility,transcriptomics
Classifier: Programming Language :: Python :: 3
Requires-Python: >=3.8
Requires-Dist: datashader
Requires-Dist: pathlibfs
Requires-Dist: polyptich>=0.0.17
Provides-Extra: dev
Requires-Dist: pre-commit; extra == "dev"
Requires-Dist: pytest; extra == "dev"
Requires-Dist: coverage; extra == "dev"
Requires-Dist: black; extra == "dev"
Requires-Dist: pylint; extra == "dev"
Requires-Dist: jupytext; extra == "dev"
Requires-Dist: mkdocs; extra == "dev"
Requires-Dist: mkdocs-material; extra == "dev"
Requires-Dist: mkdocstrings[python]; extra == "dev"
Requires-Dist: mkdocs-jupyter; extra == "dev"
Requires-Dist: mike; extra == "dev"
Requires-Dist: cairosvg; extra == "dev"
Requires-Dist: pillow; extra == "dev"
Requires-Dist: mkdocs-awesome-pages-plugin; extra == "dev"
Requires-Dist: setuptools_scm; extra == "dev"
Requires-Dist: Cython; extra == "dev"
Requires-Dist: laflow; extra == "dev"
Provides-Extra: test
Requires-Dist: pytest; extra == "test"
Requires-Dist: ruff; extra == "test"
